{
  "taylor-swift": {
    "spotifyId": "06HL4z0CvFAxyc27GXpf02",
    "name": "Taylor Swift",
    "monthlyListeners": 101530516
  },
  "the-beatles": {
    "spotifyId": "3WrFJ7ztbogyGnTHbHJFl2",
    "name": "The Beatles",
    "monthlyListeners": 36050443
  },
  "drake": {
    "spotifyId": "3TVXtAsR1Inumwj472S9r4",
    "name": "Drake",
    "monthlyListeners": 98362893
  },
  "billie-eilish": {
    "spotifyId": "6qqNVTkY8uBg9cP3Jd7DAH",
    "name": "Billie Eilish",
    "monthlyListeners": 84419902
  },
  "beyonce": {
    "spotifyId": "6vWDO969PvNqNYHIOW5v0m",
    "name": "Beyoncé",
    "monthlyListeners": 61232020
  },
  "bad-bunny": {
    "spotifyId": "4q3ewBCX7sLwd24euuV69X",
    "name": "Bad Bunny",
    "monthlyListeners": 100080812
  },
  "bts": {
    "spotifyId": "3Nrfpe0tUJi4K4DXYWgMUX",
    "name": "BTS",
    "monthlyListeners": 37818601
  },
  "olivia-rodrigo": {
    "spotifyId": "1McMsnEElThX1knmY4oliG",
    "name": "Olivia Rodrigo",
    "monthlyListeners": 60720622
  },
  "harry-styles": {
    "spotifyId": "6KImCVD70vtIoJWnq6nGn3",
    "name": "Harry Styles",
    "monthlyListeners": 66367471
  },
  "ed-sheeran": {
    "spotifyId": "6eUKZXaKkcviH0Ku9w2n3V",
    "name": "Ed Sheeran",
    "monthlyListeners": 86275811
  },
  "adele": {
    "spotifyId": "4dpARuHxo51G3z768sgnrY",
    "name": "Adele",
    "monthlyListeners": 59632968
  },
  "the-weeknd": {
    "spotifyId": "1Xyo4u8uXC1ZmMpatF05PJ",
    "name": "The Weeknd",
    "monthlyListeners": 115405242
  },
  "bob-dylan": {
    "spotifyId": "74ASZWbe4lXaubB36ztrGX",
    "name": "Bob Dylan",
    "monthlyListeners": 15024220
  },
  "david-bowie": {
    "spotifyId": "0oSGxfWSnnOXhD2fKuz2Gy",
    "name": "David Bowie",
    "monthlyListeners": 21138233
  },
  "pink-floyd": {
    "spotifyId": "0k17h0D3J5VfsdmQ1iZtE9",
    "name": "Pink Floyd",
    "monthlyListeners": 27654994
  },
  "nirvana": {
    "spotifyId": "6olE6TJLqED3rqDCT0FyPh",
    "name": "Nirvana",
    "monthlyListeners": 38928611
  },
  "queen": {
    "spotifyId": "1dfeR4HaWDbWqFHLkxsg1d",
    "name": "Queen",
    "monthlyListeners": 54687929
  },
  "phoebe-bridgers": {
    "spotifyId": "1r1uxoy19fzMxunt3ONAkG",
    "name": "Phoebe Bridgers",
    "monthlyListeners": 11559001
  },
  "mitski": {
    "spotifyId": "2uYWxilOVlUdk4oV9DvwqK",
    "name": "Mitski",
    "monthlyListeners": 20332647
  },
  "japanese-breakfast": {
    "spotifyId": "7MoIc5s9KXolCBH1fy9kkw",
    "name": "Japanese Breakfast",
    "monthlyListeners": null,
    "dailyStreams": 220237
  },
  "alvvays": {
    "spotifyId": "3kzwYV3OCB010YfXMF0Avt",
    "name": "Alvvays",
    "monthlyListeners": null,
    "dailyStreams": 190983
  },
  "big-thief": {
    "spotifyId": "5QdyldG4Fl4TPiOIeMNpBZ",
    "name": "Big Thief",
    "monthlyListeners": 5879463
  },
  "bon-iver": {
    "spotifyId": "4LEiUm1SRbFMgfqnQTwUbQ",
    "name": "Bon Iver",
    "monthlyListeners": 15584996
  },
  "vampire-weekend": {
    "spotifyId": "5BvJzeQpmsdsFp4HGUYUEx",
    "name": "Vampire Weekend",
    "monthlyListeners": null,
    "dailyStreams": 392935
  },
  "arcade-fire": {
    "spotifyId": "3kjuyTCjPG1WMFCiyc5IuB",
    "name": "Arcade Fire",
    "monthlyListeners": null,
    "dailyStreams": 540161
  },
  "radiohead": {
    "spotifyId": "4Z8W4fKeB5YxbusRsdQVPb",
    "name": "Radiohead",
    "monthlyListeners": 44397308
  },
  "fleetwood-mac": {
    "spotifyId": "08GQAI4eElDnROBrJRGE0X",
    "name": "Fleetwood Mac",
    "monthlyListeners": 53228049
  },
  "kanye-west": {
    "spotifyId": "5K4W6rqBFWDnAN6FQUkS6x",
    "name": "Kanye West",
    "monthlyListeners": 72552173
  },
  "frank-ocean": {
    "spotifyId": "2h93pZq0e7k5yf4dywlkpM",
    "name": "Frank Ocean",
    "monthlyListeners": 40820285
  },
  "tyler-the-creator": {
    "spotifyId": "4V8LLVI7PbaPR0K2TGSxFF",
    "name": "Tyler, The Creator",
    "monthlyListeners": 39897544
  },
  "king-gizzard": {
    "spotifyId": "6XYvaoDGE0VmRt83Jss9Sn",
    "name": "King Gizzard & The Lizard Wizard",
    "monthlyListeners": null,
    "dailyStreams": 19461
  },
  "weyes-blood": {
    "spotifyId": "3Uqu1mEdkUJxPe7s31n1M9",
    "name": "Weyes Blood",
    "monthlyListeners": null,
    "dailyStreams": 209886
  },
  "sufjan-stevens": {
    "spotifyId": "4MXUO7sVCaFgFjoTI5ox5c",
    "name": "Sufjan Stevens",
    "monthlyListeners": 14066292
  },
  "soccer-mommy": {
    "spotifyId": "4wXchxfTTggLtzkoUhO86Q",
    "name": "Soccer Mommy",
    "monthlyListeners": null,
    "dailyStreams": 48872
  },
  "snail-mail": {
    "spotifyId": "4QkSD9TRUnMtI8Fq1jXJJe",
    "name": "Snail Mail",
    "monthlyListeners": null,
    "dailyStreams": 89577
  },
  "faye-webster": {
    "spotifyId": "5szilpXHcwOqnyKLqGco5j",
    "name": "Faye Webster",
    "monthlyListeners": 7884933
  },
  "black-country-new-road": {
    "spotifyId": "3PP6ghmOlDl2jaKaH0avUN",
    "name": "Black Country, New Road",
    "monthlyListeners": null,
    "dailyStreams": 193727
  },
  "caroline-polachek": {
    "spotifyId": "4Ge8xMJNwt6EEXOzVXju9a",
    "name": "Caroline Polachek",
    "monthlyListeners": null,
    "dailyStreams": 395654
  },
  "cocteau-twins": {
    "spotifyId": "5Wabl1lPdNOeIn0SQ5A1mp",
    "name": "Cocteau Twins",
    "monthlyListeners": null,
    "dailyStreams": 1082771
  },
  "my-bloody-valentine": {
    "spotifyId": "3G3Gdm0ZRAOxLrbyjfhii5",
    "name": "my bloody valentine",
    "monthlyListeners": null,
    "dailyStreams": 156547
  },
  "slowdive": {
    "spotifyId": "72X6FHxaShda0XeQw3vbeF",
    "name": "Slowdive",
    "monthlyListeners": null,
    "dailyStreams": 612989
  },
  "beach-house": {
    "spotifyId": "56ZTgzPBDge0OvCGgMO3OY",
    "name": "Beach House",
    "monthlyListeners": 15600123
  },
  "mac-demarco": {
    "spotifyId": "3Sz7ZnJQBIHsXLUSo0OQtM",
    "name": "Mac DeMarco",
    "monthlyListeners": 21399941
  },
  "tame-impala": {
    "spotifyId": "5INjqkS1o8h1imAzPqGZBb",
    "name": "Tame Impala",
    "monthlyListeners": 63540422
  },
  "father-john-misty": {
    "spotifyId": "2kGBy2WHvF0VdZyqiVCkDT",
    "name": "Father John Misty",
    "monthlyListeners": 9385302
  },
  "st-vincent": {
    "spotifyId": "7bcbShaqKdcyjnmv4Ix8j6",
    "name": "St. Vincent",
    "monthlyListeners": null,
    "dailyStreams": 368752
  },
  "daft-punk": {
    "spotifyId": "4tZwfgrHOc3mvqYlEYSvVi",
    "name": "Daft Punk",
    "monthlyListeners": 30266510
  },
  "aphex-twin": {
    "spotifyId": "6kBDZFXuLrZgHnvmPu9NsG",
    "name": "Aphex Twin",
    "monthlyListeners": null,
    "dailyStreams": 644605
  },
  "boards-of-canada": {
    "spotifyId": "2VAvhf61GgLYmC6C8anyX1",
    "name": "Boards of Canada",
    "monthlyListeners": null,
    "dailyStreams": 314658
  },
  "justin-bieber": {
    "spotifyId": "1uNFoZAHBGtllmzznpCI3s",
    "name": "Justin Bieber",
    "monthlyListeners": 139032420
  },
  "david-guetta": {
    "spotifyId": "1Cs0zKBU1kc0i8ypK3B9ai",
    "name": "David Guetta",
    "monthlyListeners": 88389728
  },
  "pitbull": {
    "spotifyId": "0TnOYISbd1XYRBk9myaseg",
    "name": "Pitbull",
    "monthlyListeners": 79588478
  },
  "chris-brown": {
    "spotifyId": "7bXgB6jMjp9ATFy66eO08Z",
    "name": "Chris Brown",
    "monthlyListeners": 62410752
  },
  "olivia-dean": {
    "spotifyId": "00x1fYSGhdqScXBRpSj3DW",
    "name": "Olivia Dean",
    "monthlyListeners": 56746507
  },
  "linkin-park": {
    "spotifyId": "6XyY86QOPPrYVGvF9ch6wz",
    "name": "Linkin Park",
    "monthlyListeners": 55586619
  },
  "shawn-mendes": {
    "spotifyId": "7n2wHs1TKAczGzO7Dd2rGr",
    "name": "Shawn Mendes",
    "monthlyListeners": 51548051
  },
  "fuerza-regida": {
    "spotifyId": "0ys2OFYzWYB5hRDLCsBqxt",
    "name": "Fuerza Regida",
    "monthlyListeners": 48396636
  },
  "one-direction": {
    "spotifyId": "4AK6F7OLvEQ5QYCBNiQWHq",
    "name": "One Direction",
    "monthlyListeners": 47093563
  },
  "daniel-caesar": {
    "spotifyId": "20wkVLutqVOYrc0kxFs7rA",
    "name": "Daniel Caesar",
    "monthlyListeners": 42940341
  },
  "tems": {
    "spotifyId": "687cZJR45JO7jhk1LHIbgq",
    "name": "Tems",
    "monthlyListeners": 42426803
  },
  "p-nk": {
    "spotifyId": "1KCSPY1glIKqW2TotWuXOR",
    "name": "P!nk",
    "monthlyListeners": 39031878
  },
  "benson-boone": {
    "spotifyId": "22wbnEMDvgVIAGdFeek6ET",
    "name": "Benson Boone",
    "monthlyListeners": 38761639
  },
  "feid": {
    "spotifyId": "2LRoIwlKmHjgvigdNGBHNo",
    "name": "Feid",
    "monthlyListeners": 37403825
  },
  "mariah-carey": {
    "spotifyId": "4iHNK0tOyZPYnBU7nGAgpQ",
    "name": "Mariah Carey",
    "monthlyListeners": 35398108
  },
  "jason-derulo": {
    "spotifyId": "07YZf4WDAMNwqr4jfgOZ8y",
    "name": "Jason Derulo",
    "monthlyListeners": 34897830
  },
  "noah-kahan": {
    "spotifyId": "2RQXRUsr4IW1f3mKyKsy4B",
    "name": "Noah Kahan",
    "monthlyListeners": 33821275
  },
  "oasis": {
    "spotifyId": "2DaxqgrOhkeH0fpeiQq2f4",
    "name": "Oasis",
    "monthlyListeners": 33013193
  },
  "the-cranberries": {
    "spotifyId": "7t0rwkOPGlDPEhaOcVtOt9",
    "name": "The Cranberries",
    "monthlyListeners": 32143895
  },
  "lil-baby": {
    "spotifyId": "5f7VJjfbwm532GiveGC0ZK",
    "name": "Lil Baby",
    "monthlyListeners": 31540556
  },
  "bee-gees": {
    "spotifyId": "1LZEQNv7sE11VDY3SdxQeN",
    "name": "Bee Gees",
    "monthlyListeners": 30439802
  },
  "neton-vega": {
    "spotifyId": "6pV5zH2LzjOUHaAvENdMMa",
    "name": "Neton Vega",
    "monthlyListeners": 30245611
  },
  "ava-max": {
    "spotifyId": "4npEfmQ6YuiwW1GpUmaq3F",
    "name": "Ava Max",
    "monthlyListeners": 29195819
  },
  "giveon": {
    "spotifyId": "4fxd5Ee7UefO4CUXgwJ7IP",
    "name": "GIVĒON",
    "monthlyListeners": 28959658
  },
  "malcolm-todd": {
    "spotifyId": "7eKkW1zo5uzW8kUntiiBvz",
    "name": "Malcolm Todd",
    "monthlyListeners": 28752780
  },
  "plan-b": {
    "spotifyId": "2jSGzJw0ebJLu7OLVSOcBP",
    "name": "Plan B",
    "monthlyListeners": 28279007
  },
  "tainy": {
    "spotifyId": "0GM7qgcRCORpGnfcN2tCiB",
    "name": "Tainy",
    "monthlyListeners": 27679663
  },
  "eagles": {
    "spotifyId": "0ECwFtbIWEVNwjlrfc6xoL",
    "name": "Eagles",
    "monthlyListeners": 27237669
  },
  "mohit-chauhan": {
    "spotifyId": "5GnnSrwNCGyfAU4zuIytiS",
    "name": "Mohit Chauhan",
    "monthlyListeners": 26507640
  },
  "steve-lacy": {
    "spotifyId": "57vWImR43h4CaDao012Ofp",
    "name": "Steve Lacy",
    "monthlyListeners": 26281805
  },
  "chris-stapleton": {
    "spotifyId": "4YLtscXsxbVgi031ovDDdh",
    "name": "Chris Stapleton",
    "monthlyListeners": 25955903
  },
  "tory-lanez": {
    "spotifyId": "2jku7tDXc6XoB6MO2hFuqg",
    "name": "Tory Lanez",
    "monthlyListeners": 25106135
  },
  "martin-garrix": {
    "spotifyId": "60d24wfXkVzDSfLS6hyCjZ",
    "name": "Martin Garrix",
    "monthlyListeners": 24694365
  },
  "sexyy-red": {
    "spotifyId": "3DbwFQlvLxRSi2uX8mf81A",
    "name": "Sexyy Red",
    "monthlyListeners": 23698438
  },
  "mike-posner": {
    "spotifyId": "2KsP6tYLJlTBvSUxnwlVWa",
    "name": "Mike Posner",
    "monthlyListeners": 23451724
  },
  "jasmine-sandlas": {
    "spotifyId": "0mJDQBWytBhOh5JB1DOQ1c",
    "name": "Jasmine Sandlas",
    "monthlyListeners": 22874864
  },
  "meghan-trainor": {
    "spotifyId": "6JL8zeS1NmiOftqZTRgdTz",
    "name": "Meghan Trainor",
    "monthlyListeners": 22361943
  },
  "vishal-dadlani": {
    "spotifyId": "6CXEwIaXYfVJ84biCxqc9k",
    "name": "Vishal Dadlani",
    "monthlyListeners": 22063468
  },
  "jessie-j": {
    "spotifyId": "2gsggkzM5R49q6jpPvazou",
    "name": "Jessie J",
    "monthlyListeners": 21786678
  },
  "gabito-ballesteros": {
    "spotifyId": "6Sbl0NT50roqWvy746MfVf",
    "name": "Gabito Ballesteros",
    "monthlyListeners": 21148241
  },
  "5-seconds-of-summer": {
    "spotifyId": "5Rl15oVamLq7FbSb0NNBNy",
    "name": "5 Seconds of Summer",
    "monthlyListeners": 20681633
  },
  "mora": {
    "spotifyId": "0Q8NcsJwoCbZOHHW63su5S",
    "name": "Mora",
    "monthlyListeners": 20417397
  },
  "jelly-roll": {
    "spotifyId": "19k8AgwwTSxeaxkOuCQEJs",
    "name": "Jelly Roll",
    "monthlyListeners": 20034581
  },
  "roddy-ricch": {
    "spotifyId": "757aE44tKEUQEqRuT6GnEB",
    "name": "Roddy Ricch",
    "monthlyListeners": 19859049
  },
  "dei-v": {
    "spotifyId": "2YRyPiW98bpkARAS4B3OQP",
    "name": "Dei V",
    "monthlyListeners": 19610543
  },
  "the-lumineers": {
    "spotifyId": "16oZKvXb6WkQlVAjwo2Wbg",
    "name": "The Lumineers",
    "monthlyListeners": 19343424
  },
  "stephen-sanchez": {
    "spotifyId": "5XKFrudbV4IiuE5WuTPRmT",
    "name": "Stephen Sanchez",
    "monthlyListeners": 19228039
  },
  "tulsi-kumar": {
    "spotifyId": "0T1CMVkqffHlqEk4BcAph1",
    "name": "Tulsi Kumar",
    "monthlyListeners": 19021026
  },
  "gims": {
    "spotifyId": "0GOx72r5AAEKRGQFn3xqXK",
    "name": "GIMS",
    "monthlyListeners": 18881997
  },
  "ceelo-green": {
    "spotifyId": "5nLYd9ST4Cnwy6NHaCxbj8",
    "name": "CeeLo Green",
    "monthlyListeners": 18636101
  },
  "karan-aujla": {
    "spotifyId": "6DARBhWbfcS9E4yJzcliqQ",
    "name": "Karan Aujla",
    "monthlyListeners": 18285668
  },
  "los-angeles-azules": {
    "spotifyId": "0ZCO8oVkMj897cKgFH7fRW",
    "name": "Los Ángeles Azules",
    "monthlyListeners": 18182278
  },
  "mon-laferte": {
    "spotifyId": "4boI7bJtmB1L3b1cuL75Zr",
    "name": "Mon Laferte",
    "monthlyListeners": 18052729
  },
  "t-i": {
    "spotifyId": "4OBJLual30L7gRl5UkeRcT",
    "name": "T.I.",
    "monthlyListeners": 17702075
  },
  "de-la-rose": {
    "spotifyId": "54seKvtsZauR1iauN0ptpo",
    "name": "De La Rose",
    "monthlyListeners": 17571930
  },
  "lukas-graham": {
    "spotifyId": "25u4wHJWxCA9vO0CzxAbK7",
    "name": "Lukas Graham",
    "monthlyListeners": 17316316
  },
  "stromae": {
    "spotifyId": "5j4HeCoUlzhfWtjAfM1acR",
    "name": "Stromae",
    "monthlyListeners": 16961240
  },
  "eurythmics": {
    "spotifyId": "0NKDgy9j66h3DLnN8qu1bB",
    "name": "Eurythmics",
    "monthlyListeners": 16864417
  },
  "willow": {
    "spotifyId": "3rWZHrfrsPBxVy692yAIxF",
    "name": "WILLOW",
    "monthlyListeners": 16533280
  },
  "ms-lauryn-hill": {
    "spotifyId": "2Mu5NfyYm8n5iTomuKAEHl",
    "name": "Ms. Lauryn Hill",
    "monthlyListeners": 16470229
  },
  "gabry-ponte": {
    "spotifyId": "5ENS85nZShljwNgg4wFD7D",
    "name": "Gabry Ponte",
    "monthlyListeners": 16341984
  },
  "paul-mccartney": {
    "spotifyId": "4STHEaNw4mPZ2tzheohgXB",
    "name": "Paul McCartney",
    "monthlyListeners": 16206417
  },
  "jatin-lalit": {
    "spotifyId": "4YgUVg4p7xtMOrOS4GjiJZ",
    "name": "Jatin-Lalit",
    "monthlyListeners": 16083108
  },
  "guru-randhawa": {
    "spotifyId": "5rQoBDKFnd1n6BkdbgVaRL",
    "name": "Guru Randhawa",
    "monthlyListeners": 16003869
  },
  "cage-the-elephant": {
    "spotifyId": "26T3LtbuGT1Fu9m0eRq5X3",
    "name": "Cage The Elephant",
    "monthlyListeners": 15892706
  },
  "taio-cruz": {
    "spotifyId": "6MF9fzBmfXghAz953czmBC",
    "name": "Taio Cruz",
    "monthlyListeners": 15814785
  },
  "portugal-the-man": {
    "spotifyId": "4kI8Ie27vjvonwaB2ePh8T",
    "name": "Portugal. The Man",
    "monthlyListeners": 15514788
  },
  "the-smashing-pumpkins": {
    "spotifyId": "40Yq4vzPs9VNUrIBG5Jr2i",
    "name": "The Smashing Pumpkins",
    "monthlyListeners": 15251159
  },
  "nate-ruess": {
    "spotifyId": "1qUjOF5fzrpoNycD36b2jZ",
    "name": "Nate Ruess",
    "monthlyListeners": 15210391
  },
  "b-praak": {
    "spotifyId": "56SjZARoEvag3RoKWIb16j",
    "name": "B Praak",
    "monthlyListeners": 14840540
  },
  "galantis": {
    "spotifyId": "4sTQVOfp9vEMCemLw50sbu",
    "name": "Galantis",
    "monthlyListeners": 14696300
  },
  "hector-el-father": {
    "spotifyId": "2TjgzYcbTdsZjbT9OItIeB",
    "name": "Héctor \"El Father\"",
    "monthlyListeners": 14527607
  },
  "brytiago": {
    "spotifyId": "00XhexlJEXQstHimpZN910",
    "name": "Brytiago",
    "monthlyListeners": 14300526
  },
  "esdeekid": {
    "spotifyId": "0EyhkwP3UnwGFBy6xwKjSy",
    "name": "EsDeeKid",
    "monthlyListeners": 14268072
  },
  "la-oreja-de-van-gogh": {
    "spotifyId": "4U7lXyKdSf1JbM1aXvsodC",
    "name": "La Oreja de Van Gogh",
    "monthlyListeners": 14052634
  },
  "sai-abhyankkar": {
    "spotifyId": "5jJrJU7VVmxQQLcLAmmxXc",
    "name": "Sai Abhyankkar",
    "monthlyListeners": 13983167
  },
  "starship": {
    "spotifyId": "0kObWap02DEg9EAJ3PBxzf",
    "name": "Starship",
    "monthlyListeners": 13920071
  },
  "gesaffelstein": {
    "spotifyId": "3hteYQFiMFbJY7wS0xDymP",
    "name": "Gesaffelstein",
    "monthlyListeners": 13757871
  },
  "melanie-martinez": {
    "spotifyId": "63yrD80RY3RNEM2YDpUpO8",
    "name": "Melanie Martinez",
    "monthlyListeners": 13618461
  },
  "van-halen": {
    "spotifyId": "2cnMpRsOVqtPMfq7YiFE6K",
    "name": "Van Halen",
    "monthlyListeners": 13479298
  },
  "lloyd": {
    "spotifyId": "1Xfmvd48oOhEWkscWyEbh9",
    "name": "Lloyd",
    "monthlyListeners": 13389249
  },
  "new-west": {
    "spotifyId": "69bG9tC62d8oTFC9aTTosn",
    "name": "New West",
    "monthlyListeners": 13170839
  },
  "rudimental": {
    "spotifyId": "4WN5naL3ofxrVBgFpguzKo",
    "name": "Rudimental",
    "monthlyListeners": 13022165
  },
  "chris-isaak": {
    "spotifyId": "7290H8m1Dwt8G7jm1y9CQx",
    "name": "Chris Isaak",
    "monthlyListeners": 12829825
  },
  "ciara": {
    "spotifyId": "2NdeV5rLm47xAvogXrYhJX",
    "name": "Ciara",
    "monthlyListeners": 12683096
  },
  "marilia-mendonca": {
    "spotifyId": "1yR65psqiazQpeM79CcGh8",
    "name": "Marília Mendonça",
    "monthlyListeners": 12612012
  },
  "jay-sean": {
    "spotifyId": "4pADjHPWyrlAF0FA7joK2H",
    "name": "Jay Sean",
    "monthlyListeners": 12538050
  },
  "shenseea": {
    "spotifyId": "1OFOShsIbhy1l5x73yuVyB",
    "name": "Shenseea",
    "monthlyListeners": 12395622
  },
  "jazzy": {
    "spotifyId": "7zAAwgV5Wqmvpb4GzvlRkP",
    "name": "Jazzy",
    "monthlyListeners": 12249965
  },
  "hombres-g": {
    "spotifyId": "60uh2KYYSCqAgJNxcU4DA0",
    "name": "Hombres G",
    "monthlyListeners": 12214513
  },
  "r3hab": {
    "spotifyId": "6cEuCEZu7PAE9ZSzLLc2oQ",
    "name": "R3HAB",
    "monthlyListeners": 12188318
  },
  "clementine-douglas": {
    "spotifyId": "4DWuml4Jf6K81b5rAPwMb6",
    "name": "Clementine Douglas",
    "monthlyListeners": 12070355
  },
  "jere-klein": {
    "spotifyId": "35oGZihZclGoTVuICPXRP9",
    "name": "Jere Klein",
    "monthlyListeners": 12021242
  },
  "luke-bryan": {
    "spotifyId": "0BvkDsjIUla7X0k6CSWh1I",
    "name": "Luke Bryan",
    "monthlyListeners": 11966260
  },
  "oliver-tree": {
    "spotifyId": "6TLwD7HPWuiOzvXEa3oCNe",
    "name": "Oliver Tree",
    "monthlyListeners": 11783535
  },
  "the-magician": {
    "spotifyId": "4WUGQykLBGFfsl0Qjl6TDM",
    "name": "The Magician",
    "monthlyListeners": 11692620
  },
  "m": {
    "spotifyId": "0bdfiayQAKewqEvaU6rXCv",
    "name": "MØ",
    "monthlyListeners": 11513314
  },
  "070-shake": {
    "spotifyId": "12Zk1DFhCbHY6v3xep2ZjI",
    "name": "070 Shake",
    "monthlyListeners": 11417280
  },
  "ilaiyaraaja": {
    "spotifyId": "0ti7TORoorlhGPSRUkz129",
    "name": "Ilaiyaraaja",
    "monthlyListeners": 11358340
  },
  "soundgarden": {
    "spotifyId": "5xUf6j4upBrXZPg6AI4MRK",
    "name": "Soundgarden",
    "monthlyListeners": 11150509
  },
  "the-rare-occasions": {
    "spotifyId": "1QfpRUtH14JLoY6F6AYmwt",
    "name": "The Rare Occasions",
    "monthlyListeners": 11074742
  },
  "andy-grammer": {
    "spotifyId": "2oX42qP5ineK3hrhBECLmj",
    "name": "Andy Grammer",
    "monthlyListeners": 10916979
  },
  "pet-shop-boys": {
    "spotifyId": "2ycnb8Er79LoH2AsR5ldjh",
    "name": "Pet Shop Boys",
    "monthlyListeners": 10714484
  },
  "naresh-iyer": {
    "spotifyId": "7FaGCZiP3s6X7jQTB8EhfI",
    "name": "Naresh Iyer",
    "monthlyListeners": 10696092
  },
  "coi-leray": {
    "spotifyId": "6AMd49uBDJfhf30Ak2QR5s",
    "name": "Coi Leray",
    "monthlyListeners": 10607723
  },
  "intocable": {
    "spotifyId": "108moq3rq6bm1M4Ypz0J02",
    "name": "Intocable",
    "monthlyListeners": 10504015
  },
  "third-eye-blind": {
    "spotifyId": "6TcnmlCSxihzWOQJ8k0rNS",
    "name": "Third Eye Blind",
    "monthlyListeners": 10468954
  },
  "dan-shay": {
    "spotifyId": "7z5WFjZAIYejWy0NI5lv4T",
    "name": "Dan + Shay",
    "monthlyListeners": 10262547
  },
  "strawberry-guy": {
    "spotifyId": "1AbJ2cmwK400LSvdvBL5Jc",
    "name": "Strawberry Guy",
    "monthlyListeners": 10247563
  },
  "alanis-morissette": {
    "spotifyId": "6ogn9necmbUdCppmNnGOdi",
    "name": "Alanis Morissette",
    "monthlyListeners": 10215469
  },
  "cutting-crew": {
    "spotifyId": "3cniTumSiUysiPWXapGx1i",
    "name": "Cutting Crew",
    "monthlyListeners": 10135895
  },
  "staind": {
    "spotifyId": "5KDIH2gF0VpelTqyQS7udb",
    "name": "Staind",
    "monthlyListeners": 10111327
  },
  "pierce-the-veil": {
    "spotifyId": "4iJLPqClelZOBCBifm8Fzv",
    "name": "Pierce The Veil",
    "monthlyListeners": 10066269
  },
  "elevation-worship": {
    "spotifyId": "3YCKuqpv9nCsIhJ2v8SMix",
    "name": "Elevation Worship",
    "monthlyListeners": 9970729
  },
  "genesis": {
    "spotifyId": "3CkvROUTQ6nRi9yQOcsB50",
    "name": "Genesis",
    "monthlyListeners": 9843354
  },
  "spandau-ballet": {
    "spotifyId": "2urZrEdsq72kx0UzfYN8Yv",
    "name": "Spandau Ballet",
    "monthlyListeners": 9815461
  },
  "iann-dior": {
    "spotifyId": "6ASri4ePR7RlsvIQgWPJpS",
    "name": "iann dior",
    "monthlyListeners": 9728657
  },
  "missy-elliott": {
    "spotifyId": "2wIVse2owClT7go1WT98tk",
    "name": "Missy Elliott",
    "monthlyListeners": 9695163
  },
  "joao-gomes": {
    "spotifyId": "4JNo6Q5KdcRf1vtSX9mB0S",
    "name": "João Gomes",
    "monthlyListeners": 9570107
  },
  "otis-redding": {
    "spotifyId": "60df5JBRRPcnSpsIMxxwQm",
    "name": "Otis Redding",
    "monthlyListeners": 9551031
  },
  "the-temptations": {
    "spotifyId": "3RwQ26hR2tJtA8F9p2n7jG",
    "name": "The Temptations",
    "monthlyListeners": 9535907
  },
  "d-o-d": {
    "spotifyId": "0Cs47vvRsPgEfliBU9KDiB",
    "name": "D.O.D",
    "monthlyListeners": 9452819
  },
  "arko": {
    "spotifyId": "6jf2eKjiPT6P18RbOSLzf0",
    "name": "Arko",
    "monthlyListeners": 9425065
  },
  "mc-pedrinho": {
    "spotifyId": "1etNnR2SdlelBQAICa2Q5m",
    "name": "Mc Pedrinho",
    "monthlyListeners": 9378893
  },
  "nina-simone": {
    "spotifyId": "7G1GBhoKtEPnP86X2PvEYO",
    "name": "Nina Simone",
    "monthlyListeners": 9269925
  },
  "sujatha": {
    "spotifyId": "2JEjaa7hWhE1BbL3OcoeFR",
    "name": "Sujatha",
    "monthlyListeners": 9236201
  },
  "nas": {
    "spotifyId": "20qISvAhX20dpIbOOzGK3q",
    "name": "Nas",
    "monthlyListeners": 9077647
  },
  "dasha": {
    "spotifyId": "7Ez6lTtSMjMf2YSYpukP1I",
    "name": "Dasha",
    "monthlyListeners": 9010220
  },
  "kevin-gates": {
    "spotifyId": "1gPhS1zisyXr5dHTYZyiMe",
    "name": "Kevin Gates",
    "monthlyListeners": 8979330
  },
  "the-cars": {
    "spotifyId": "6DCIj8jNaNpBz8e5oKFPtp",
    "name": "The Cars",
    "monthlyListeners": 8878975
  },
  "gopi-sundar": {
    "spotifyId": "4xlqU0G9EloUPHL1qlmWY6",
    "name": "Gopi Sundar",
    "monthlyListeners": 8856889
  },
  "riton": {
    "spotifyId": "7i9j813KFoSBMldGqlh2Z1",
    "name": "Riton",
    "monthlyListeners": 8778788
  },
  "kaytranada": {
    "spotifyId": "6qgnBH6iDM91ipVXv28OMu",
    "name": "KAYTRANADA",
    "monthlyListeners": 8739778
  },
  "vacations": {
    "spotifyId": "0U7iI0Dk4Ojvi17nZboNO4",
    "name": "Vacations",
    "monthlyListeners": 8677454
  },
  "royel-otis": {
    "spotifyId": "5b5bt4mZQpJMoCRbiQ7diH",
    "name": "Royel Otis",
    "monthlyListeners": 8654158
  },
  "young-the-giant": {
    "spotifyId": "4j56EQDQu5XnL7R3E9iFJT",
    "name": "Young the Giant",
    "monthlyListeners": 8599395
  },
  "flow-g": {
    "spotifyId": "3PDFGpPl4ienSn5Vwisfrh",
    "name": "Flow G",
    "monthlyListeners": 8558942
  },
  "dread-mar-i": {
    "spotifyId": "1aw0Cdl1DIrtUrUA6fGbAR",
    "name": "Dread Mar I",
    "monthlyListeners": 8509265
  },
  "loud-luxury": {
    "spotifyId": "6t1gpxYbY8OlLA7D2RiikQ",
    "name": "Loud Luxury",
    "monthlyListeners": 8489904
  },
  "marta-sanchez": {
    "spotifyId": "368rTiMKMrz3b03az6B14w",
    "name": "Marta Sánchez",
    "monthlyListeners": 8476236
  },
  "tiakola": {
    "spotifyId": "3vUMXQ9kPnZAQkMkZZ7Hfh",
    "name": "Tiakola",
    "monthlyListeners": 8294476
  },
  "dexter-and-the-moonrocks": {
    "spotifyId": "72sOBVpZpUwHq7i0vb26lT",
    "name": "Dexter and The Moonrocks",
    "monthlyListeners": 8183472
  },
  "r-k-m-and-ken-y": {
    "spotifyId": "3jFjgKOGfVLWfXX8q5wrsg",
    "name": "R.K.M & Ken-Y",
    "monthlyListeners": 8163870
  },
  "leon-larregui": {
    "spotifyId": "4ClsVDy2g7RKSSlvq8cF6d",
    "name": "León Larregui",
    "monthlyListeners": 8116193
  },
  "kahitna": {
    "spotifyId": "2WhoMc7XqIzVXWbQqSoqe7",
    "name": "Kahitna",
    "monthlyListeners": 8091638
  },
  "shinedown": {
    "spotifyId": "70BYFdaZbEKbeauJ670ysI",
    "name": "Shinedown",
    "monthlyListeners": 8076439
  },
  "jp-cooper": {
    "spotifyId": "4kYGAK2zu9EAomwj3hXkXy",
    "name": "JP Cooper",
    "monthlyListeners": 8036915
  },
  "loreen": {
    "spotifyId": "49aaHxvAJ0tCh0F15OnwIl",
    "name": "Loreen",
    "monthlyListeners": 7993514
  },
  "sky-rompiendo": {
    "spotifyId": "51XrH5fQP2oIQynuKxSWcW",
    "name": "Sky Rompiendo",
    "monthlyListeners": 7962663
  },
  "oh-wonder": {
    "spotifyId": "5cIc3SBFuBLVxJz58W2tU9",
    "name": "Oh Wonder",
    "monthlyListeners": 7940615
  },
  "commodores": {
    "spotifyId": "6twIAGnYuIT1pncMAsXnEm",
    "name": "Commodores",
    "monthlyListeners": 7919961
  },
  "zeze-di-camargo-and-luciano": {
    "spotifyId": "4dyYjqmYDjegbB3F2mbvcT",
    "name": "Zezé Di Camargo & Luciano",
    "monthlyListeners": 7824037
  },
  "europe": {
    "spotifyId": "7Js6Lde8thlIHXggv2SCBz",
    "name": "Europe",
    "monthlyListeners": 7797620
  },
  "a-touch-of-class": {
    "spotifyId": "5wTdspmxzb8V4ZjvDodpBo",
    "name": "A Touch Of Class",
    "monthlyListeners": 7755198
  },
  "majestic": {
    "spotifyId": "6QMABvTzixnxzsLYyhqRxI",
    "name": "Majestic",
    "monthlyListeners": 7714653
  },
  "damian-marley": {
    "spotifyId": "3QJzdZJYIAcoET1GcfpNGi",
    "name": "Damian Marley",
    "monthlyListeners": 7655191
  },
  "wallows": {
    "spotifyId": "0NIPkIjTV8mB795yEIiPYL",
    "name": "Wallows",
    "monthlyListeners": 7627541
  },
  "dexys-midnight-runners": {
    "spotifyId": "4QTVePrFu1xuGM9K0kNXkk",
    "name": "Dexys Midnight Runners",
    "monthlyListeners": 7440886
  },
  "the-proclaimers": {
    "spotifyId": "1A92IAcd7A6npCA33oGM5i",
    "name": "The Proclaimers",
    "monthlyListeners": 7324452
  },
  "player": {
    "spotifyId": "0fgtHVpOPfXb07S8Jx443z",
    "name": "Player",
    "monthlyListeners": 7276224
  },
  "mc-kevin": {
    "spotifyId": "5pBMkZNIlbGTH3hrsQJqAa",
    "name": "Mc Kevin",
    "monthlyListeners": 7228957
  },
  "sandro-cavazza": {
    "spotifyId": "5JYo7gm2dkyLLlWHjxS7Dy",
    "name": "Sandro Cavazza",
    "monthlyListeners": 7197433
  },
  "hippie-sabotage": {
    "spotifyId": "4dM6NDYSfLcspt8GLoT5aE",
    "name": "Hippie Sabotage",
    "monthlyListeners": 7146257
  },
  "sofiya-nzau": {
    "spotifyId": "5Y2FS5YbGf7yRDumzD5nY3",
    "name": "Sofiya Nzau",
    "monthlyListeners": 7105089
  },
  "why-don-t-we": {
    "spotifyId": "2jnIB6XdLvnJUeNTy5A0J2",
    "name": "Why Don't We",
    "monthlyListeners": 7083768
  },
  "shalmali-kholgade": {
    "spotifyId": "6uskWv5K2FA0YOAYr7JOUz",
    "name": "Shalmali Kholgade",
    "monthlyListeners": 7035768
  },
  "charly-black": {
    "spotifyId": "5sK8BsvyDl4TFA6KaBf8or",
    "name": "Charly Black",
    "monthlyListeners": 7013919
  },
  "baby-gang": {
    "spotifyId": "3LvwPiJQJ0da0GurKMToV0",
    "name": "Baby Gang",
    "monthlyListeners": 6999131
  },
  "vengaboys": {
    "spotifyId": "0cwmNvclzPd8mQnoHuIksj",
    "name": "Vengaboys",
    "monthlyListeners": 6934573
  },
  "chimbala": {
    "spotifyId": "4VVEpEhC8NcR7AqNEds42U",
    "name": "Chimbala",
    "monthlyListeners": 6918109
  },
  "five-finger-death-punch": {
    "spotifyId": "5t28BP42x2axFnqOOMg3CM",
    "name": "Five Finger Death Punch",
    "monthlyListeners": 6865844
  },
  "42-dugg": {
    "spotifyId": "45gHcnDnMC15sgx3VL7ROG",
    "name": "42 Dugg",
    "monthlyListeners": 6800783
  },
  "ebru-gundes": {
    "spotifyId": "5AboYJAlMb9FGadTTDKRoN",
    "name": "Ebru Gündeş",
    "monthlyListeners": 6788772
  },
  "toni-braxton": {
    "spotifyId": "3X458ddYA2YcVWuVIGGOYe",
    "name": "Toni Braxton",
    "monthlyListeners": 6732929
  },
  "mariah-the-scientist": {
    "spotifyId": "7HO5fOXE4gh3lzZn64tX2E",
    "name": "Mariah the Scientist",
    "monthlyListeners": 6717434
  },
  "amanda-miguel": {
    "spotifyId": "3v8mFhjLFa50QK8zDvAMYN",
    "name": "Amanda Miguel",
    "monthlyListeners": 6701217
  },
  "gurinder-gill": {
    "spotifyId": "5DHi2MeoRgAwPE0A0qwRMl",
    "name": "Gurinder Gill",
    "monthlyListeners": 6660083
  },
  "djavan": {
    "spotifyId": "5rrmaoBXZ7Jcs4Qb77j0YA",
    "name": "Djavan",
    "monthlyListeners": 6651404
  },
  "camelphat": {
    "spotifyId": "240wlM8vDrf6S4zCyzGj2W",
    "name": "CamelPhat",
    "monthlyListeners": 6631073
  },
  "guaynaa": {
    "spotifyId": "0BqURncJM5B1BBu7UM51eq",
    "name": "Guaynaa",
    "monthlyListeners": 6553040
  },
  "bossman-dlow": {
    "spotifyId": "23xFbA9rYgRX8mreqysWPc",
    "name": "BossMan Dlow",
    "monthlyListeners": 6535751
  },
  "bjork": {
    "spotifyId": "7w29UYBi0qsHi5RTcv3lmA",
    "name": "Björk",
    "monthlyListeners": 6454128
  },
  "sanjith-hegde": {
    "spotifyId": "1plObTufEAfeL1hk8Qz24v",
    "name": "Sanjith Hegde",
    "monthlyListeners": 6435824
  },
  "dilsinho": {
    "spotifyId": "4NUePmzDvCYqilXBFa91Hg",
    "name": "Dilsinho",
    "monthlyListeners": 6378046
  },
  "lucenzo": {
    "spotifyId": "5bv5RplEOwdCvhq0EILh9E",
    "name": "Lucenzo",
    "monthlyListeners": 6342044
  },
  "israel-kamakawiwo-ole": {
    "spotifyId": "4ogvuDRerGhZfSf7TtzHlr",
    "name": "Israel Kamakawiwo'ole",
    "monthlyListeners": 6319761
  },
  "rupert-holmes": {
    "spotifyId": "0TqIPD4IS1w4e30R38B3vj",
    "name": "Rupert Holmes",
    "monthlyListeners": 6304800
  },
  "up-dharma-down": {
    "spotifyId": "3wbCeEPAW6po7J46netxMT",
    "name": "Up Dharma Down",
    "monthlyListeners": 6254913
  },
  "roberto-carlos": {
    "spotifyId": "7fAKtXSdNInWAIf0jVUz65",
    "name": "Roberto Carlos",
    "monthlyListeners": 6246730
  },
  "abhay-jodhpurkar": {
    "spotifyId": "27rK4pP0VMqWiRe7pamKe5",
    "name": "Abhay Jodhpurkar",
    "monthlyListeners": 6186751
  },
  "noah": {
    "spotifyId": "31aMmlq8isIAgojvmIwiS4",
    "name": "Noah",
    "monthlyListeners": 6136980
  },
  "the-paper-kites": {
    "spotifyId": "79hrYiudVcFyyxyJW0ipTy",
    "name": "The Paper Kites",
    "monthlyListeners": 6116725
  },
  "dynoro": {
    "spotifyId": "3v6Ji4uoWtKRkhuDUaxi9n",
    "name": "Dynoro",
    "monthlyListeners": 6037955
  },
  "twista": {
    "spotifyId": "6vbY3hOaCAhC7VjucswgdS",
    "name": "Twista",
    "monthlyListeners": 6021098
  },
  "snoh-aalegra": {
    "spotifyId": "1A9o3Ljt67pFZ89YtPPL5X",
    "name": "Snoh Aalegra",
    "monthlyListeners": 5973305
  },
  "sleepy-hallow": {
    "spotifyId": "6EPlBSH2RSiettczlz7ihV",
    "name": "Sleepy Hallow",
    "monthlyListeners": 5943822
  },
  "tinlicker": {
    "spotifyId": "5EmEZjq8eHEC6qFnT63Lza",
    "name": "Tinlicker",
    "monthlyListeners": 5929255
  },
  "dhee": {
    "spotifyId": "77YvCBWe0tTLygpgSJsdOH",
    "name": "Dhee",
    "monthlyListeners": 5891882
  },
  "baby-rasta-y-gringo": {
    "spotifyId": "3IEvQoAohcGX7CdrbtIle7",
    "name": "Baby Rasta y Gringo",
    "monthlyListeners": 5875583
  },
  "the-la-s": {
    "spotifyId": "47Z8LEl3LnQkcpva0xSthT",
    "name": "The La's",
    "monthlyListeners": 5868492
  },
  "bruno-mars": {
    "spotifyId": "0du5cEVh5yTK9QJze8zA0C",
    "name": "Bruno Mars",
    "monthlyListeners": 138326855
  },
  "j-balvin": {
    "spotifyId": "1vyhD5VmyZ7KMfW5gqLgo5",
    "name": "J Balvin",
    "monthlyListeners": 72954027
  },
  "post-malone": {
    "spotifyId": "246dkjvS1zLTtiykXe5h60",
    "name": "Post Malone",
    "monthlyListeners": 62231461
  },
  "alex-warren": {
    "spotifyId": "0fTSzq9jAh4c36UVb4V7CB",
    "name": "Alex Warren",
    "monthlyListeners": 51243836
  },
  "a-r-rahman": {
    "spotifyId": "1mYsTxnqsietFxj1OgoGbG",
    "name": "A.R. Rahman",
    "monthlyListeners": 48621554
  },
  "diplo": {
    "spotifyId": "5fMUXHkw8R8eOP2RNVYEZX",
    "name": "Diplo",
    "monthlyListeners": 42518020
  },
  "gorillaz": {
    "spotifyId": "3AA28KZvwAUcZuOKwyblJQ",
    "name": "Gorillaz",
    "monthlyListeners": 40370852
  },
  "the-killers": {
    "spotifyId": "0C0XlULifJtAgn6ZNCW2eu",
    "name": "The Killers",
    "monthlyListeners": 36261622
  },
  "morgan-wallen": {
    "spotifyId": "4oUHIQIBe0LHzYfvXNW4QM",
    "name": "Morgan Wallen",
    "monthlyListeners": 35175365
  },
  "ravyn-lenae": {
    "spotifyId": "5RTLRtXjbXI2lSXc6jxlAz",
    "name": "Ravyn Lenae",
    "monthlyListeners": 32594462
  },
  "ryan-castro": {
    "spotifyId": "7j6DKwmjbxvpQO8h914uEz",
    "name": "Ryan Castro",
    "monthlyListeners": 31113924
  },
  "shashwat-sachdev": {
    "spotifyId": "465OXuCU8YZNmVG1leLwQ9",
    "name": "Shashwat Sachdev",
    "monthlyListeners": 29764567
  },
  "kehlani": {
    "spotifyId": "0cGUm45nv7Z6M6qdXYQGTX",
    "name": "Kehlani",
    "monthlyListeners": 29137668
  },
  "hugel": {
    "spotifyId": "5PlfkPxwCpRRWQJBxCa0By",
    "name": "HUGEL",
    "monthlyListeners": 28230173
  },
  "lewis-capaldi": {
    "spotifyId": "4GNC7GD6oZMSxPGyXy4MNB",
    "name": "Lewis Capaldi",
    "monthlyListeners": 26367436
  },
  "macklemore-and-ryan-lewis": {
    "spotifyId": "5BcAKTbp20cv7tC5VqPFoC",
    "name": "Macklemore & Ryan Lewis",
    "monthlyListeners": 25702459
  },
  "maneskin": {
    "spotifyId": "0lAWpj5szCSwM4rUMHYmrr",
    "name": "Måneskin",
    "monthlyListeners": 24421851
  },
  "the-jackson-5": {
    "spotifyId": "2iE18Oxc8YSumAU232n4rW",
    "name": "The Jackson 5",
    "monthlyListeners": 23483893
  },
  "r-e-m": {
    "spotifyId": "4KWTAlx2RvbpseOGMEmROg",
    "name": "R.E.M.",
    "monthlyListeners": 22190318
  },
  "luis-r-conriquez": {
    "spotifyId": "0pePYDrJGk8gqMRbXrLJC8",
    "name": "Luis R Conriquez",
    "monthlyListeners": 21706185
  },
  "tove-lo": {
    "spotifyId": "4NHQUGzhtTLFvgF5SZesLK",
    "name": "Tove Lo",
    "monthlyListeners": 20552974
  },
  "d4vd": {
    "spotifyId": "5y8tKLUfMvliMe8IKamR32",
    "name": "d4vd",
    "monthlyListeners": 20312151
  },
  "felix-jaehn": {
    "spotifyId": "4bL2B6hmLlMWnUEZnorEtG",
    "name": "Felix Jaehn",
    "monthlyListeners": 19750254
  },
  "santana": {
    "spotifyId": "6GI52t8N5F02MxU0g5U69P",
    "name": "Santana",
    "monthlyListeners": 19472005
  },
  "s-p-balasubrahmanyam": {
    "spotifyId": "2ae6PxICSOZHvjqiCcgon8",
    "name": "S. P. Balasubrahmanyam",
    "monthlyListeners": 18737304
  },
  "grupo-marca-registrada": {
    "spotifyId": "1gW6pz5n1aK249L0GvfQCC",
    "name": "Grupo Marca Registrada",
    "monthlyListeners": 18362911
  },
  "electric-light-orchestra": {
    "spotifyId": "7jefIIksOi1EazgRTfW2Pk",
    "name": "Electric Light Orchestra",
    "monthlyListeners": 18111176
  },
  "joan-sebastian": {
    "spotifyId": "7FsRH5bw8iWpSbMX1G7xf1",
    "name": "Joan Sebastian",
    "monthlyListeners": 17485047
  },
  "la-arrolladora-banda-el-limon-de-rene-camacho": {
    "spotifyId": "5bSfBBCxY8QAk4Pifveisz",
    "name": "La Arrolladora Banda El Limón De Rene Camacho",
    "monthlyListeners": 17312880
  },
  "madhubanti-bagchi": {
    "spotifyId": "4ojkMVHjuDZgDXSJy5qs2h",
    "name": "Madhubanti Bagchi",
    "monthlyListeners": 16852106
  },
  "milo-j": {
    "spotifyId": "19HM5j0ULGSmEoRcrSe5x3",
    "name": "Milo j",
    "monthlyListeners": 16533815
  },
  "depeche-mode": {
    "spotifyId": "762310PdDnwsDxAQxzQkfX",
    "name": "Depeche Mode",
    "monthlyListeners": 15879384
  },
  "gajendra-verma": {
    "spotifyId": "1yzgJmZf5CxtFfGfRFm4Si",
    "name": "Gajendra Verma",
    "monthlyListeners": 15730197
  },
  "rod-stewart": {
    "spotifyId": "2y8Jo9CKhJvtfeKOsYzRdT",
    "name": "Rod Stewart",
    "monthlyListeners": 15389283
  },
  "sadhana-sargam": {
    "spotifyId": "1HGMG8RHvcu1mfdM9MeTek",
    "name": "Sadhana Sargam",
    "monthlyListeners": 15213939
  },
  "ace-of-base": {
    "spotifyId": "5ksRONqssB7BR161NTtJAm",
    "name": "Ace of Base",
    "monthlyListeners": 14514639
  },
  "6lack": {
    "spotifyId": "4IVAbR2w4JJNJDDRFP3E83",
    "name": "6LACK",
    "monthlyListeners": 14435609
  },
  "hoobastank": {
    "spotifyId": "2MqhkhX4npxDZ62ObR5ELO",
    "name": "Hoobastank",
    "monthlyListeners": 14096165
  },
  "shaan": {
    "spotifyId": "5cB4d4jPYjMT326sjihQ4m",
    "name": "Shaan",
    "monthlyListeners": 13938164
  },
  "lmfao": {
    "spotifyId": "3sgFRtyBnxXD5ESfmbK4dl",
    "name": "LMFAO",
    "monthlyListeners": 13815279
  },
  "quavo": {
    "spotifyId": "0VRj0yCOv2FXJNP47XQnx5",
    "name": "Quavo",
    "monthlyListeners": 12931860
  },
  "natalia-lafourcade": {
    "spotifyId": "1hcdI2N1023RvSwLzTtdsp",
    "name": "Natalia Lafourcade",
    "monthlyListeners": 12684639
  },
  "4-non-blondes": {
    "spotifyId": "0Je74SitssvJg1w4Ra2EK7",
    "name": "4 Non Blondes",
    "monthlyListeners": 12496491
  },
  "tommy-richman": {
    "spotifyId": "1WaFQSHVGZQJTbf0BdxdNo",
    "name": "Tommy Richman",
    "monthlyListeners": 12362314
  },
  "juan-magan": {
    "spotifyId": "1ackd5XprZEkH3McKbQD51",
    "name": "Juan Magán",
    "monthlyListeners": 12162956
  },
  "dj-nelson": {
    "spotifyId": "2ydZrTy8U3kOMOzx20s3dg",
    "name": "DJ Nelson",
    "monthlyListeners": 12039494
  },
  "la-factoria": {
    "spotifyId": "00Lc7Ok0Grodr365KFTSi3",
    "name": "La Factoria",
    "monthlyListeners": 11679209
  },
  "yeah-yeah-yeahs": {
    "spotifyId": "3TNt4aUIxgfy9aoaft5Jj2",
    "name": "Yeah Yeah Yeahs",
    "monthlyListeners": 11558846
  },
  "the-doors": {
    "spotifyId": "22WZ7M8sxp5THdruNY3gXt",
    "name": "The Doors",
    "monthlyListeners": 11275571
  },
  "aretha-franklin": {
    "spotifyId": "7nwUJBm0HE4ZxD3f5cy5ok",
    "name": "Aretha Franklin",
    "monthlyListeners": 11113436
  },
  "birdy": {
    "spotifyId": "2WX2uTcsvV5OnS0inACecP",
    "name": "Birdy",
    "monthlyListeners": 10604753
  },
  "aespa": {
    "spotifyId": "6YVMFz59CuY7ngCxTxjpxE",
    "name": "aespa",
    "monthlyListeners": 10551481
  },
  "blake-shelton": {
    "spotifyId": "1UTPBmNbXNTittyMJrNkvw",
    "name": "Blake Shelton",
    "monthlyListeners": 10344307
  },
  "yahritza-y-su-esencia": {
    "spotifyId": "51ZSh80McCt7vbqHouzW0A",
    "name": "Yahritza Y Su Esencia",
    "monthlyListeners": 10203855
  },
  "frankie-ruiz": {
    "spotifyId": "4dLvccxeQIM5u80Ri0u9OV",
    "name": "Frankie Ruiz",
    "monthlyListeners": 10134765
  },
  "cafune": {
    "spotifyId": "581C5Qwl87TskfBEzuoisu",
    "name": "Cafuné",
    "monthlyListeners": 9957558
  },
  "manuel-medrano": {
    "spotifyId": "0i5iO6icb7kxg48thi9gBM",
    "name": "Manuel Medrano",
    "monthlyListeners": 9898395
  },
  "the-red-clay-strays": {
    "spotifyId": "6IKlXZEFOvk9itrP1s0knJ",
    "name": "The Red Clay Strays",
    "monthlyListeners": 9780343
  },
  "bronski-beat": {
    "spotifyId": "2wpWOzQE5TpA0dVnh5YD08",
    "name": "Bronski Beat",
    "monthlyListeners": 9719648
  },
  "role-model": {
    "spotifyId": "1dy5WNgIKQU6ezkpZs4y8z",
    "name": "ROLE MODEL",
    "monthlyListeners": 9565277
  },
  "rawayana": {
    "spotifyId": "2AbQwU2cuEGfD465wCXlg2",
    "name": "Rawayana",
    "monthlyListeners": 9530123
  },
  "carlos-baute": {
    "spotifyId": "3smfreCkyJt7bShaTYpG77",
    "name": "Carlos Baute",
    "monthlyListeners": 9352766
  },
  "grouplove": {
    "spotifyId": "3kVUvbeRdcrqQ3oHk5hPdx",
    "name": "GROUPLOVE",
    "monthlyListeners": 9272918
  },
  "jeezy": {
    "spotifyId": "4yBK75WVCQXej1p04GWqxH",
    "name": "Jeezy",
    "monthlyListeners": 9055547
  },
  "pedro-capo": {
    "spotifyId": "4QVBYiagIaa6ZGSPMbybpy",
    "name": "Pedro Capó",
    "monthlyListeners": 8842917
  },
  "the-calling": {
    "spotifyId": "5aMmmNxw4vgpc5XC6hK0zp",
    "name": "The Calling",
    "monthlyListeners": 8750923
  },
  "leo-dan": {
    "spotifyId": "6qhOH2mrlqUDod9sWA5kR2",
    "name": "Leo Dan",
    "monthlyListeners": 8586326
  },
  "mixsingh": {
    "spotifyId": "05dG9pMLRWenxzvSmefE6U",
    "name": "MixSingh",
    "monthlyListeners": 8542470
  },
  "prospa": {
    "spotifyId": "6HabM2PUM519iIxervGWSb",
    "name": "Prospa",
    "monthlyListeners": 8315909
  },
  "last-child": {
    "spotifyId": "1v1khTmozNfxB2ET1Ep288",
    "name": "Last Child",
    "monthlyListeners": 8213048
  },
  "alexis-y-fido": {
    "spotifyId": "7tU1VKOuxiNZwBZC6RHidA",
    "name": "Alexis y Fido",
    "monthlyListeners": 8065565
  },
  "big-mountain": {
    "spotifyId": "0Jeckitay8SbvKwqAzWuYH",
    "name": "Big Mountain",
    "monthlyListeners": 8025783
  },
  "isabel-larosa": {
    "spotifyId": "5arKwJZEvT5uKq4o0JfqR4",
    "name": "Isabel LaRosa",
    "monthlyListeners": 7863185
  },
  "michael-sembello": {
    "spotifyId": "771qBvjnXOH9Azr6lKy6FB",
    "name": "Michael Sembello",
    "monthlyListeners": 7797858
  },
  "ashanti": {
    "spotifyId": "5rkVyNGXEgeUqKkB5ccK83",
    "name": "Ashanti",
    "monthlyListeners": 7638727
  },
  "puddle-of-mudd": {
    "spotifyId": "3dXaa6jwM7B52GZpaJEIr5",
    "name": "Puddle Of Mudd",
    "monthlyListeners": 7556864
  },
  "redbone": {
    "spotifyId": "0w7HLMvZOHatWVbAKee1zF",
    "name": "Redbone",
    "monthlyListeners": 7506088
  },
  "jimi-hendrix": {
    "spotifyId": "776Uo845nYHJpNaStv1Ds4",
    "name": "Jimi Hendrix",
    "monthlyListeners": 7369708
  },
  "mr-belt-and-wezol": {
    "spotifyId": "19VDJ9IKyBSUMDJxLsasP6",
    "name": "Mr. Belt & Wezol",
    "monthlyListeners": 7321581
  },
  "pericles": {
    "spotifyId": "6gEzJZrbm0F4ihvE9iXR9z",
    "name": "Péricles",
    "monthlyListeners": 7256813
  },
  "the-wanted": {
    "spotifyId": "2NhdGz9EDv2FeUw6udu2g1",
    "name": "The Wanted",
    "monthlyListeners": 7172541
  },
  "mecano": {
    "spotifyId": "5BMgsAFg8rZQc3tqs5BB8G",
    "name": "Mecano",
    "monthlyListeners": 7118360
  },
  "mf-doom": {
    "spotifyId": "2pAWfrd7WFF3XhVt9GooDL",
    "name": "MF DOOM",
    "monthlyListeners": 7062672
  },
  "baby-bash": {
    "spotifyId": "12PSlydMSjEHzSCj9X5qv7",
    "name": "Baby Bash",
    "monthlyListeners": 6960381
  },
  "shouse": {
    "spotifyId": "2TcGJdSOiOvITBzhvfX8XB",
    "name": "Shouse",
    "monthlyListeners": 6913163
  },
  "nacho": {
    "spotifyId": "2ayNSoKPCRAfjp6hQ76hRu",
    "name": "Nacho",
    "monthlyListeners": 6806706
  },
  "carlos-rivera": {
    "spotifyId": "39yVoqm6sYFvvqF1RciUVf",
    "name": "Carlos Rivera",
    "monthlyListeners": 6778407
  },
  "soolking": {
    "spotifyId": "0GgY7hjMoGDsX8ZDe2mwds",
    "name": "Soolking",
    "monthlyListeners": 6707377
  },
  "chuck-berry": {
    "spotifyId": "293zczrfYafIItmnmM3coR",
    "name": "Chuck Berry",
    "monthlyListeners": 6611215
  },
  "la-sonora-dinamita": {
    "spotifyId": "13or1Wf6ipcvSIiurZATvw",
    "name": "La Sonora Dinamita",
    "monthlyListeners": 6583162
  },
  "tayc": {
    "spotifyId": "7gU9VyFRN3JWPJ5oHOil60",
    "name": "Tayc",
    "monthlyListeners": 6538708
  },
  "pooh-shiesty": {
    "spotifyId": "5F1aAS1duwlzExnPs3l2Xe",
    "name": "Pooh Shiesty",
    "monthlyListeners": 6517895
  },
  "warren-zeiders": {
    "spotifyId": "7kplJl06UmldxLKseURAYi",
    "name": "Warren Zeiders",
    "monthlyListeners": 6379162
  },
  "marisela": {
    "spotifyId": "73c2MjCAFNyKYIs7nBlqG2",
    "name": "Marisela",
    "monthlyListeners": 6328146
  },
  "bakermat": {
    "spotifyId": "3MyFDtqB80WZvbtCZRsekM",
    "name": "Bakermat",
    "monthlyListeners": 6134391
  },
  "back-number": {
    "spotifyId": "6rs1KAoQnFalSqSU4LTh8g",
    "name": "back number",
    "monthlyListeners": 6059420
  },
  "amit-kumar": {
    "spotifyId": "5l1aGNGCRGomCMHVufh6xC",
    "name": "Amit Kumar",
    "monthlyListeners": 5943676
  },
  "o-rappa": {
    "spotifyId": "1A5QJAC1vdhbhPE25Q0x0f",
    "name": "O Rappa",
    "monthlyListeners": 5929095
  },
  "dierks-bentley": {
    "spotifyId": "7x8nK0m0cP2ksQf0mjWdPS",
    "name": "Dierks Bentley",
    "monthlyListeners": 5873821
  },
  "brooke-ligertwood": {
    "spotifyId": "7iETGaxJ4crz3qaljDPCKC",
    "name": "Brooke Ligertwood",
    "monthlyListeners": 5841380
  }
}
